nic/__init__.py
nic/callbacks.py
nic/captioning.py
nic/evaluation.py
nic/metrics.py
nic/model.py
nic/training.py
nic/datapreparation/__init__.py
nic/datapreparation/data.py
nic/datapreparation/downloading.py
nic/datapreparation/preprocessing.py
nic/datapreparation/utils.py
nic-0.0.1.dist-info/LICENSE.md
nic-0.0.1.dist-info/METADATA
nic-0.0.1.dist-info/WHEEL
nic-0.0.1.dist-info/top_level.txt
nic-0.0.1.dist-info/RECORD
