Metadata-Version: 2.1
Name: nic
Version: 0.0.1
Summary: Simple API for neural image captioning with MSCOCO data
Home-page: https://github.com/StiliyanDr/neural-image-caption
Author: Stiliyan Dragnev
Author-email: stiliyan_dragnev@yahoo.com
License: MIT License
Project-URL: Bug Tracker, https://github.com/StiliyanDr/neural-image-caption/issues
Keywords: neural,image,caption,mscoco,coco
Platform: UNKNOWN
Classifier: Programming Language :: Python :: 3
Classifier: License :: OSI Approved :: MIT License
Classifier: Operating System :: OS Independent
Requires-Python: >=3.6
License-File: LICENSE.md
Requires-Dist: nltk
Requires-Dist: numpy
Requires-Dist: tensorflow
Requires-Dist: tqdm
